python_agent/__init__.py
python_agent/admin.py
python_agent/init.py
python_agent/utils.py
python_agent/bootstrap/__init__.py
python_agent/bootstrap/sitecustomize.py
python_agent/build_scanner/__init__.py
python_agent/build_scanner/app.py
python_agent/build_scanner/ast_utils.py
python_agent/build_scanner/file_scanner.py
python_agent/build_scanner/method_hasher.py
python_agent/build_scanner/visitors.py
python_agent/build_scanner/entities/__init__.py
python_agent/build_scanner/entities/environment_data.py
python_agent/build_scanner/entities/v3/__init__.py
python_agent/build_scanner/entities/v3/build_mapping_request.py
python_agent/build_scanner/entities/v3/code_element_with_hash.py
python_agent/build_scanner/entities/v3/file_data.py
python_agent/build_scanner/entities/v3/method_data.py
python_agent/build_scanner/executors/__init__.py
python_agent/build_scanner/executors/build.py
python_agent/build_scanner/executors/config.py
python_agent/build_scanner/executors/pr_config.py
python_agent/build_scanner/scm/__init__.py
python_agent/build_scanner/scm/git_integration.py
python_agent/build_scanner/scm/scm_info.py
python_agent/common/__init__.py
python_agent/common/config_data.py
python_agent/common/configuration_manager.py
python_agent/common/constants.py
python_agent/common/environment_variables_resolver.py
python_agent/common/agent_events/__init__.py
python_agent/common/agent_events/agent_events_manager.py
python_agent/common/agent_events/env_vars.py
python_agent/common/agent_events/utils.py
python_agent/common/agent_events/entites/__init__.py
python_agent/common/agent_events/entites/agent_build_scan_error_event.py
python_agent/common/agent_events/entites/agent_footprints_submission_error_event.py
python_agent/common/agent_events/entites/agent_heartbeat_event.py
python_agent/common/agent_events/entites/agent_start_event.py
python_agent/common/agent_events/entites/agent_stop_event.py
python_agent/common/agent_events/entites/agent_tests_submission_error_event.py
python_agent/serverless/sealights_layer/python/libs/certifi-2025.8.3.dist-info/licenses/LICENSE
python_agent/serverless/sealights_layer/python/libs/requests-2.32.5.dist-info/licenses/LICENSE
python_agent/serverless/sealights_layer/python/libs/urllib3-2.6.2.dist-info/licenses/LICENSE.txt
sealights_python_agent-2.7.8.dist-info/licenses/LICENSE.txt
python_agent/serverless/sealights_layer/python/libs/certifi-2025.8.3.dist-info/INSTALLER
python_agent/serverless/sealights_layer/python/libs/certifi-2025.8.3.dist-info/METADATA
python_agent/serverless/sealights_layer/python/libs/certifi-2025.8.3.dist-info/RECORD
python_agent/serverless/sealights_layer/python/libs/certifi-2025.8.3.dist-info/REQUESTED
python_agent/serverless/sealights_layer/python/libs/certifi-2025.8.3.dist-info/WHEEL
python_agent/serverless/sealights_layer/python/libs/certifi-2025.8.3.dist-info/top_level.txt
python_agent/serverless/sealights_layer/python/libs/charset_normalizer-3.2.0.dist-info/INSTALLER
python_agent/serverless/sealights_layer/python/libs/charset_normalizer-3.2.0.dist-info/LICENSE
python_agent/serverless/sealights_layer/python/libs/charset_normalizer-3.2.0.dist-info/METADATA
python_agent/serverless/sealights_layer/python/libs/charset_normalizer-3.2.0.dist-info/RECORD
python_agent/serverless/sealights_layer/python/libs/charset_normalizer-3.2.0.dist-info/WHEEL
python_agent/serverless/sealights_layer/python/libs/charset_normalizer-3.2.0.dist-info/entry_points.txt
python_agent/serverless/sealights_layer/python/libs/charset_normalizer-3.2.0.dist-info/top_level.txt
python_agent/serverless/sealights_layer/python/libs/coverage-7.3.1.dist-info/INSTALLER
python_agent/serverless/sealights_layer/python/libs/coverage-7.3.1.dist-info/LICENSE.txt
python_agent/serverless/sealights_layer/python/libs/coverage-7.3.1.dist-info/METADATA
python_agent/serverless/sealights_layer/python/libs/coverage-7.3.1.dist-info/RECORD
python_agent/serverless/sealights_layer/python/libs/coverage-7.3.1.dist-info/REQUESTED
python_agent/serverless/sealights_layer/python/libs/coverage-7.3.1.dist-info/WHEEL
python_agent/serverless/sealights_layer/python/libs/coverage-7.3.1.dist-info/entry_points.txt
python_agent/serverless/sealights_layer/python/libs/coverage-7.3.1.dist-info/top_level.txt
python_agent/serverless/sealights_layer/python/libs/idna-3.10.dist-info/INSTALLER
python_agent/serverless/sealights_layer/python/libs/idna-3.10.dist-info/LICENSE.md
python_agent/serverless/sealights_layer/python/libs/idna-3.10.dist-info/METADATA
python_agent/serverless/sealights_layer/python/libs/idna-3.10.dist-info/RECORD
python_agent/serverless/sealights_layer/python/libs/idna-3.10.dist-info/REQUESTED
python_agent/serverless/sealights_layer/python/libs/idna-3.10.dist-info/WHEEL
python_agent/serverless/sealights_layer/python/libs/requests-2.32.5.dist-info/INSTALLER
python_agent/serverless/sealights_layer/python/libs/requests-2.32.5.dist-info/METADATA
python_agent/serverless/sealights_layer/python/libs/requests-2.32.5.dist-info/RECORD
python_agent/serverless/sealights_layer/python/libs/requests-2.32.5.dist-info/REQUESTED
python_agent/serverless/sealights_layer/python/libs/requests-2.32.5.dist-info/WHEEL
python_agent/serverless/sealights_layer/python/libs/requests-2.32.5.dist-info/top_level.txt
python_agent/serverless/sealights_layer/python/libs/urllib3-2.6.2.dist-info/INSTALLER
python_agent/serverless/sealights_layer/python/libs/urllib3-2.6.2.dist-info/METADATA
python_agent/serverless/sealights_layer/python/libs/urllib3-2.6.2.dist-info/RECORD
python_agent/serverless/sealights_layer/python/libs/urllib3-2.6.2.dist-info/REQUESTED
python_agent/serverless/sealights_layer/python/libs/urllib3-2.6.2.dist-info/WHEEL
sealights_python_agent-2.7.8.dist-info/METADATA
sealights_python_agent-2.7.8.dist-info/WHEEL
sealights_python_agent-2.7.8.dist-info/entry_points.txt
sealights_python_agent-2.7.8.dist-info/top_level.txt
sealights_python_agent-2.7.8.dist-info/RECORD
