Metadata-Version: 2.4
Name: sealights_python_agent
Version: 2.7.8
Summary: Python Agent
Home-page: https://github.com/Sealights/SL.OnPremise.Agents.Python
Author: Shai Cantor
Author-email: shai@sealights.io
License: Other/Proprietary License
Keywords: sealights python agent setuptools development
Classifier: Development Status :: 5 - Production/Stable
Classifier: Intended Audience :: Developers
Classifier: Topic :: Software Development :: Build Tools
Classifier: License :: Other/Proprietary License
Classifier: Programming Language :: Python :: 3.7
Classifier: Programming Language :: Python :: 3.8
Classifier: Programming Language :: Python :: 3.9
Classifier: Programming Language :: Python :: 3.10
Classifier: Programming Language :: Python :: 3.11
Classifier: Programming Language :: Python :: 3.12
Classifier: Programming Language :: Python :: 3.13
Requires-Python: >=3.7, <4
License-File: LICENSE.txt
Requires-Dist: colorama==0.4.6
Requires-Dist: pytz==2022.6; python_version >= "3.7"
Requires-Dist: six==1.16.0
Requires-Dist: tzlocal==4.2
Requires-Dist: backports.zoneinfo==0.2.1; python_version < "3.9"
Requires-Dist: importlib-resources==5.4.0; python_version < "3.7"
Requires-Dist: pytz-deprecation-shim==0.1.0.post0
Requires-Dist: tzdata==2022.1; platform_system == "Windows"
Requires-Dist: zipp==3.19.1; python_version < "3.10"
Requires-Dist: cryptography<46.0.0,>=44.0.0; python_version >= "3.6.8" and python_version < "3.8"
Requires-Dist: cryptography>=46.0.1; python_version >= "3.8"
Requires-Dist: cffi==1.15.1; python_version >= "3.7" and python_version < "3.9"
Requires-Dist: cffi>=2.0.0; python_version >= "3.9"
Requires-Dist: pycparser==2.21
Requires-Dist: GitPython>=3.1.35; python_version >= "3.7" and python_version < "3.13"
Requires-Dist: GitPython>=3.1.40; python_version >= "3.13"
Requires-Dist: gitdb==4.0.9
Requires-Dist: smmap==5.0.0
Requires-Dist: typing-extensions==4.1.1; python_version < "3.8"
Requires-Dist: unittest_xml_reporting==3.1.0
Requires-Dist: urllib3<2.0,>=1.26.20; python_version < "3.9"
Requires-Dist: urllib3>=2.6.2; python_version >= "3.9"
Requires-Dist: requests<2.32,>=2.31.0; python_version == "3.7"
Requires-Dist: requests<2.32.5,>=2.32.4; python_version == "3.8"
Requires-Dist: requests>=2.32.5; python_version >= "3.9"
Requires-Dist: idna>=3.10
Requires-Dist: certifi>=2025.8.3
Provides-Extra: dev
Requires-Dist: check-manifest; extra == "dev"
Provides-Extra: test
Requires-Dist: coverage; extra == "test"
Dynamic: author
Dynamic: author-email
Dynamic: classifier
Dynamic: description
Dynamic: home-page
Dynamic: keywords
Dynamic: license
Dynamic: license-file
Dynamic: provides-extra
Dynamic: requires-dist
Dynamic: requires-python
Dynamic: summary
